{
  "data" : [
  {
  "html" : "https://vamosy.github.io/ddsport/1.html",
  "img" : "https://res.cloudinary.com/dbz90kpq0/image/upload/v1659053898/dd/1_jzhaby.jpg",
  "name" : "ADVICE 1"
  },
  {
  "html" : "https://vamosy.github.io/ddsport/2.html",
  "img" : "https://res.cloudinary.com/dbz90kpq0/image/upload/v1659053898/dd/1_jzhaby.jpg",
  "name" : "ADVICE 2"
  },
  {
  "html" : "https://vamosy.github.io/ddsport/3.html",
  "img" : "https://res.cloudinary.com/dbz90kpq0/image/upload/v1659053898/dd/1_jzhaby.jpg",
  "name" : "ADVICE 3"
  },
  {
  "html" : "https://vamosy.github.io/ddsport/4.html",
  "img" : "https://res.cloudinary.com/dbz90kpq0/image/upload/v1659053898/dd/1_jzhaby.jpg",
  "name" : "ADVICE 4"
  },
  {
  "html" : "https://vamosy.github.io/ddsport/5.html",
  "img" : "https://res.cloudinary.com/dbz90kpq0/image/upload/v1659053898/dd/1_jzhaby.jpg",
  "name" : "ADVICE 5"
  },
  {
  "html" : "https://vamosy.github.io/ddsport/6.html",
  "img" : "https://res.cloudinary.com/dbz90kpq0/image/upload/v1659053898/dd/1_jzhaby.jpg",
  "name" : "ADVICE 6"
  },
  {
  "html" : "https://vamosy.github.io/ddsport/7.html",
  "img" : "https://res.cloudinary.com/dbz90kpq0/image/upload/v1659053898/dd/1_jzhaby.jpg",
  "name" : "ADVICE 7"
  }
    ,
  {
  "html" : "https://vamosy.github.io/ddsport/8.html",
  "img" : "https://res.cloudinary.com/dbz90kpq0/image/upload/v1659053898/dd/1_jzhaby.jpg",
  "name" : "ADVICE 5"
  },
  {
  "html" : "https://vamosy.github.io/ddsport/9.html",
  "img" : "https://res.cloudinary.com/dbz90kpq0/image/upload/v1659053898/dd/1_jzhaby.jpg",
  "name" : "ADVICE 6"
  },
  {
  "html" : "https://vamosy.github.io/ddsport/10.html",
  "img" : "https://res.cloudinary.com/dbz90kpq0/image/upload/v1659053898/dd/1_jzhaby.jpg",
  "name" : "ADVICE 7"
  }
    ]
  }
