 {
  "data" : [
  {
  "html" : "https://vamosy.github.io/playcin/1.html",
  "img" : "https://res.cloudinary.com/dbz90kpq0/image/upload/v1661441532/playcin/1_g9plj8.jpg",
  "name" : "TIPS 1"
  },
  {
  "html" : "https://vamosy.github.io/playcin/2.html",
  "img" : "https://res.cloudinary.com/dbz90kpq0/image/upload/v1661441532/playcin/2_rwq8yx.jpg",
  "name" : "TIPS 2"
  },
  {
  "html" : "https://vamosy.github.io/playcin/3.html",
  "img" : "https://res.cloudinary.com/dbz90kpq0/image/upload/v1661441532/playcin/3_ohnbfy.jpg",
  "name" : "TIPS 3"
  },
  {
  "html" : "https://vamosy.github.io/playcin/4.html",
  "img" : "https://res.cloudinary.com/dbz90kpq0/image/upload/v1661441533/playcin/4_zvl18k.jpg",
  "name" : "TIPS 4"
  },
  {
  "html" : "https://vamosy.github.io/playcin/5.html",
  "img" : "https://res.cloudinary.com/dbz90kpq0/image/upload/v1661441534/playcin/5_zi0qdy.jpg",
  "name" : "TIPS 5"
  },
  {
  "html" : "https://vamosy.github.io/playcin/6.html",
  "img" : "https://res.cloudinary.com/dbz90kpq0/image/upload/v1661441539/playcin/6_ewsicv.jpg",
  "name" : "TIPS 6"
  }
    
    ]
  }
